{"size":8,"latinSquare":[[2,6,7,1,4,8,3,5],[8,3,5,4,6,2,1,7],[3,8,1,5,7,4,6,2],[4,7,6,2,3,5,8,1],[5,1,8,7,2,3,4,6],[6,4,2,3,5,1,7,8],[1,2,4,6,8,7,5,3],[7,5,3,8,1,6,2,4]],"cages":[{"value":1,"op":"N","cells":[{"row":3,"col":7,"position":32,"value":1,"borders":{"top":1,"rgt":1,"btm":1,"lft":1}}],"size":1},{"size":2,"value":16,"cells":[{"row":0,"col":0,"position":1,"value":2,"borders":{"top":1,"rgt":1,"btm":0,"lft":1}},{"row":1,"col":0,"position":9,"value":8,"borders":{"top":0,"rgt":1,"btm":1,"lft":1}}],"op":"*"},{"value":6,"op":"N","cells":[{"row":5,"col":0,"position":41,"value":6,"borders":{"top":1,"rgt":1,"btm":1,"lft":1}}],"size":1},{"size":2,"value":18,"cells":[{"row":0,"col":1,"position":2,"value":6,"borders":{"top":1,"rgt":1,"btm":0,"lft":1}},{"row":1,"col":1,"position":10,"value":3,"borders":{"top":0,"rgt":1,"btm":1,"lft":1}}],"op":"*"},{"size":2,"value":7,"cells":[{"row":0,"col":2,"position":3,"value":7,"borders":{"top":1,"rgt":0,"btm":1,"lft":1}},{"row":0,"col":3,"position":4,"value":1,"borders":{"top":1,"rgt":1,"btm":1,"lft":0}}],"op":"*"},{"size":2,"value":32,"cells":[{"row":0,"col":4,"position":5,"value":4,"borders":{"top":1,"rgt":0,"btm":1,"lft":1}},{"row":0,"col":5,"position":6,"value":8,"borders":{"top":1,"rgt":1,"btm":1,"lft":0}}],"op":"*"},{"size":2,"value":2,"cells":[{"row":0,"col":6,"position":7,"value":3,"borders":{"top":1,"rgt":0,"btm":1,"lft":1}},{"row":0,"col":7,"position":8,"value":5,"borders":{"top":1,"rgt":1,"btm":1,"lft":0}}],"op":"-"},{"size":2,"value":1,"cells":[{"row":1,"col":2,"position":11,"value":5,"borders":{"top":1,"rgt":0,"btm":1,"lft":1}},{"row":1,"col":3,"position":12,"value":4,"borders":{"top":1,"rgt":1,"btm":1,"lft":0}}],"op":"-"},{"size":2,"value":13,"cells":[{"row":1,"col":4,"position":13,"value":6,"borders":{"top":1,"rgt":1,"btm":0,"lft":1}},{"row":2,"col":4,"position":21,"value":7,"borders":{"top":0,"rgt":1,"btm":1,"lft":1}}],"op":"+"},{"size":2,"value":2,"cells":[{"row":1,"col":5,"position":14,"value":2,"borders":{"top":1,"rgt":1,"btm":0,"lft":1}},{"row":2,"col":5,"position":22,"value":4,"borders":{"top":0,"rgt":1,"btm":1,"lft":1}}],"op":"-"},{"size":2,"value":5,"cells":[{"row":1,"col":6,"position":15,"value":1,"borders":{"top":1,"rgt":1,"btm":0,"lft":1}},{"row":2,"col":6,"position":23,"value":6,"borders":{"top":0,"rgt":1,"btm":1,"lft":1}}],"op":"-"},{"value":3,"op":"N","cells":[{"row":3,"col":4,"position":29,"value":3,"borders":{"top":1,"rgt":1,"btm":1,"lft":1}}],"size":1},{"value":1,"op":"N","cells":[{"row":4,"col":1,"position":34,"value":1,"borders":{"top":1,"rgt":1,"btm":1,"lft":1}}],"size":1},{"size":2,"value":14,"cells":[{"row":1,"col":7,"position":16,"value":7,"borders":{"top":1,"rgt":1,"btm":0,"lft":1}},{"row":2,"col":7,"position":24,"value":2,"borders":{"top":0,"rgt":1,"btm":1,"lft":1}}],"op":"*"},{"size":2,"value":11,"cells":[{"row":2,"col":0,"position":17,"value":3,"borders":{"top":1,"rgt":0,"btm":1,"lft":1}},{"row":2,"col":1,"position":18,"value":8,"borders":{"top":1,"rgt":1,"btm":1,"lft":0}}],"op":"+"},{"size":2,"value":5,"cells":[{"row":2,"col":2,"position":19,"value":1,"borders":{"top":1,"rgt":1,"btm":0,"lft":1}},{"row":3,"col":2,"position":27,"value":6,"borders":{"top":0,"rgt":1,"btm":1,"lft":1}}],"op":"-"},{"value":2,"op":"N","cells":[{"row":5,"col":2,"position":43,"value":2,"borders":{"top":1,"rgt":1,"btm":1,"lft":1}}],"size":1},{"size":2,"value":7,"cells":[{"row":2,"col":3,"position":20,"value":5,"borders":{"top":1,"rgt":1,"btm":0,"lft":1}},{"row":3,"col":3,"position":28,"value":2,"borders":{"top":0,"rgt":1,"btm":1,"lft":1}}],"op":"+"},{"size":2,"value":1,"cells":[{"row":3,"col":0,"position":25,"value":4,"borders":{"top":1,"rgt":1,"btm":0,"lft":1}},{"row":4,"col":0,"position":33,"value":5,"borders":{"top":0,"rgt":1,"btm":1,"lft":1}}],"op":"-"},{"size":2,"value":2,"cells":[{"row":3,"col":5,"position":30,"value":5,"borders":{"top":1,"rgt":1,"btm":0,"lft":1}},{"row":4,"col":5,"position":38,"value":3,"borders":{"top":0,"rgt":1,"btm":1,"lft":1}}],"op":"-"},{"size":2,"value":12,"cells":[{"row":3,"col":6,"position":31,"value":8,"borders":{"top":1,"rgt":1,"btm":0,"lft":1}},{"row":4,"col":6,"position":39,"value":4,"borders":{"top":0,"rgt":1,"btm":1,"lft":1}}],"op":"+"},{"size":2,"value":56,"cells":[{"row":4,"col":2,"position":35,"value":8,"borders":{"top":1,"rgt":0,"btm":1,"lft":1}},{"row":4,"col":3,"position":36,"value":7,"borders":{"top":1,"rgt":1,"btm":1,"lft":0}}],"op":"*"},{"size":2,"value":7,"cells":[{"row":4,"col":4,"position":37,"value":2,"borders":{"top":1,"rgt":1,"btm":0,"lft":1}},{"row":5,"col":4,"position":45,"value":5,"borders":{"top":0,"rgt":1,"btm":1,"lft":1}}],"op":"+"},{"size":2,"value":2,"cells":[{"row":4,"col":7,"position":40,"value":6,"borders":{"top":1,"rgt":1,"btm":0,"lft":1}},{"row":5,"col":7,"position":48,"value":8,"borders":{"top":0,"rgt":1,"btm":1,"lft":1}}],"op":"-"},{"value":3,"op":"N","cells":[{"row":7,"col":2,"position":59,"value":3,"borders":{"top":1,"rgt":1,"btm":1,"lft":1}}],"size":1},{"size":2,"value":6,"cells":[{"row":5,"col":1,"position":42,"value":4,"borders":{"top":1,"rgt":1,"btm":0,"lft":1}},{"row":6,"col":1,"position":50,"value":2,"borders":{"top":0,"rgt":1,"btm":1,"lft":1}}],"op":"+"},{"size":2,"value":3,"cells":[{"row":5,"col":3,"position":44,"value":3,"borders":{"top":1,"rgt":1,"btm":0,"lft":1}},{"row":6,"col":3,"position":52,"value":6,"borders":{"top":0,"rgt":1,"btm":1,"lft":1}}],"op":"-"},{"size":2,"value":7,"cells":[{"row":5,"col":5,"position":46,"value":1,"borders":{"top":1,"rgt":0,"btm":1,"lft":1}},{"row":5,"col":6,"position":47,"value":7,"borders":{"top":1,"rgt":1,"btm":1,"lft":0}}],"op":"*"},{"value":2,"op":"N","cells":[{"row":7,"col":6,"position":63,"value":2,"borders":{"top":1,"rgt":1,"btm":1,"lft":1}}],"size":1},{"size":2,"value":7,"cells":[{"row":6,"col":0,"position":49,"value":1,"borders":{"top":1,"rgt":1,"btm":0,"lft":1}},{"row":7,"col":0,"position":57,"value":7,"borders":{"top":0,"rgt":1,"btm":1,"lft":1}}],"op":"*"},{"size":2,"value":9,"cells":[{"row":6,"col":4,"position":53,"value":8,"borders":{"top":1,"rgt":1,"btm":0,"lft":1}},{"row":7,"col":4,"position":61,"value":1,"borders":{"top":0,"rgt":1,"btm":1,"lft":1}}],"op":"+"},{"size":2,"value":12,"cells":[{"row":6,"col":5,"position":54,"value":7,"borders":{"top":1,"rgt":0,"btm":1,"lft":1}},{"row":6,"col":6,"position":55,"value":5,"borders":{"top":1,"rgt":1,"btm":1,"lft":0}}],"op":"+"},{"size":2,"value":12,"cells":[{"row":6,"col":7,"position":56,"value":3,"borders":{"top":1,"rgt":1,"btm":0,"lft":1}},{"row":7,"col":7,"position":64,"value":4,"borders":{"top":0,"rgt":1,"btm":1,"lft":1}}],"op":"*"},{"size":1,"value":5,"cells":[{"row":7,"col":1,"position":58,"value":5,"borders":{"top":1,"rgt":1,"btm":1,"lft":1}}],"op":"N"},{"size":1,"value":6,"cells":[{"row":7,"col":5,"position":62,"value":6,"borders":{"top":1,"rgt":1,"btm":1,"lft":1}}],"op":"N"},{"value":4,"op":"N","cells":[{"row":6,"col":2,"position":51,"value":4,"borders":{"top":1,"rgt":1,"btm":1,"lft":1}}],"size":1},{"value":8,"op":"N","cells":[{"row":7,"col":3,"position":60,"value":8,"borders":{"top":1,"rgt":1,"btm":1,"lft":1}}],"size":1},{"value":7,"op":"N","cells":[{"row":3,"col":1,"position":26,"value":7,"borders":{"top":1,"rgt":1,"btm":1,"lft":1}}],"size":1}],"ops":["+","-","*"],"viewBoard":[[{"cageId":2,"position":1,"value":2,"top":1,"rgt":1,"btm":0,"lft":1,"hint":"16X"},{"cageId":4,"position":2,"value":6,"top":1,"rgt":1,"btm":0,"lft":1,"hint":"18X"},{"cageId":5,"position":3,"value":7,"top":1,"rgt":0,"btm":1,"lft":1,"hint":"7X"},{"cageId":5,"position":4,"value":1,"top":1,"rgt":1,"btm":1,"lft":0,"hint":""},{"cageId":6,"position":5,"value":4,"top":1,"rgt":0,"btm":1,"lft":1,"hint":"32X"},{"cageId":6,"position":6,"value":8,"top":1,"rgt":1,"btm":1,"lft":0,"hint":""},{"cageId":7,"position":7,"value":3,"top":1,"rgt":0,"btm":1,"lft":1,"hint":"2-"},{"cageId":7,"position":8,"value":5,"top":1,"rgt":1,"btm":1,"lft":0,"hint":""}],[{"cageId":2,"position":9,"value":8,"top":0,"rgt":1,"btm":1,"lft":1,"hint":""},{"cageId":4,"position":10,"value":3,"top":0,"rgt":1,"btm":1,"lft":1,"hint":""},{"cageId":8,"position":11,"value":5,"top":1,"rgt":0,"btm":1,"lft":1,"hint":"1-"},{"cageId":8,"position":12,"value":4,"top":1,"rgt":1,"btm":1,"lft":0,"hint":""},{"cageId":9,"position":13,"value":6,"top":1,"rgt":1,"btm":0,"lft":1,"hint":"13+"},{"cageId":10,"position":14,"value":2,"top":1,"rgt":1,"btm":0,"lft":1,"hint":"2-"},{"cageId":11,"position":15,"value":1,"top":1,"rgt":1,"btm":0,"lft":1,"hint":"5-"},{"cageId":14,"position":16,"value":7,"top":1,"rgt":1,"btm":0,"lft":1,"hint":"14X"}],[{"cageId":15,"position":17,"value":3,"top":1,"rgt":0,"btm":1,"lft":1,"hint":"11+"},{"cageId":15,"position":18,"value":8,"top":1,"rgt":1,"btm":1,"lft":0,"hint":""},{"cageId":16,"position":19,"value":1,"top":1,"rgt":1,"btm":0,"lft":1,"hint":"5-"},{"cageId":18,"position":20,"value":5,"top":1,"rgt":1,"btm":0,"lft":1,"hint":"7+"},{"cageId":9,"position":21,"value":7,"top":0,"rgt":1,"btm":1,"lft":1,"hint":""},{"cageId":10,"position":22,"value":4,"top":0,"rgt":1,"btm":1,"lft":1,"hint":""},{"cageId":11,"position":23,"value":6,"top":0,"rgt":1,"btm":1,"lft":1,"hint":""},{"cageId":14,"position":24,"value":2,"top":0,"rgt":1,"btm":1,"lft":1,"hint":""}],[{"cageId":19,"position":25,"value":4,"top":1,"rgt":1,"btm":0,"lft":1,"hint":"1-"},{"cageId":38,"position":26,"value":7,"top":1,"rgt":1,"btm":1,"lft":1,"hint":"7"},{"cageId":16,"position":27,"value":6,"top":0,"rgt":1,"btm":1,"lft":1,"hint":""},{"cageId":18,"position":28,"value":2,"top":0,"rgt":1,"btm":1,"lft":1,"hint":""},{"cageId":12,"position":29,"value":3,"top":1,"rgt":1,"btm":1,"lft":1,"hint":"3"},{"cageId":20,"position":30,"value":5,"top":1,"rgt":1,"btm":0,"lft":1,"hint":"2-"},{"cageId":21,"position":31,"value":8,"top":1,"rgt":1,"btm":0,"lft":1,"hint":"12+"},{"cageId":1,"position":32,"value":1,"top":1,"rgt":1,"btm":1,"lft":1,"hint":"1"}],[{"cageId":19,"position":33,"value":5,"top":0,"rgt":1,"btm":1,"lft":1,"hint":""},{"cageId":13,"position":34,"value":1,"top":1,"rgt":1,"btm":1,"lft":1,"hint":"1"},{"cageId":22,"position":35,"value":8,"top":1,"rgt":0,"btm":1,"lft":1,"hint":"56X"},{"cageId":22,"position":36,"value":7,"top":1,"rgt":1,"btm":1,"lft":0,"hint":""},{"cageId":23,"position":37,"value":2,"top":1,"rgt":1,"btm":0,"lft":1,"hint":"7+"},{"cageId":20,"position":38,"value":3,"top":0,"rgt":1,"btm":1,"lft":1,"hint":""},{"cageId":21,"position":39,"value":4,"top":0,"rgt":1,"btm":1,"lft":1,"hint":""},{"cageId":24,"position":40,"value":6,"top":1,"rgt":1,"btm":0,"lft":1,"hint":"2-"}],[{"cageId":3,"position":41,"value":6,"top":1,"rgt":1,"btm":1,"lft":1,"hint":"6"},{"cageId":26,"position":42,"value":4,"top":1,"rgt":1,"btm":0,"lft":1,"hint":"6+"},{"cageId":17,"position":43,"value":2,"top":1,"rgt":1,"btm":1,"lft":1,"hint":"2"},{"cageId":27,"position":44,"value":3,"top":1,"rgt":1,"btm":0,"lft":1,"hint":"3-"},{"cageId":23,"position":45,"value":5,"top":0,"rgt":1,"btm":1,"lft":1,"hint":""},{"cageId":28,"position":46,"value":1,"top":1,"rgt":0,"btm":1,"lft":1,"hint":"7X"},{"cageId":28,"position":47,"value":7,"top":1,"rgt":1,"btm":1,"lft":0,"hint":""},{"cageId":24,"position":48,"value":8,"top":0,"rgt":1,"btm":1,"lft":1,"hint":""}],[{"cageId":30,"position":49,"value":1,"top":1,"rgt":1,"btm":0,"lft":1,"hint":"7X"},{"cageId":26,"position":50,"value":2,"top":0,"rgt":1,"btm":1,"lft":1,"hint":""},{"cageId":36,"position":51,"value":4,"top":1,"rgt":1,"btm":1,"lft":1,"hint":"4"},{"cageId":27,"position":52,"value":6,"top":0,"rgt":1,"btm":1,"lft":1,"hint":""},{"cageId":31,"position":53,"value":8,"top":1,"rgt":1,"btm":0,"lft":1,"hint":"9+"},{"cageId":32,"position":54,"value":7,"top":1,"rgt":0,"btm":1,"lft":1,"hint":"12+"},{"cageId":32,"position":55,"value":5,"top":1,"rgt":1,"btm":1,"lft":0,"hint":""},{"cageId":33,"position":56,"value":3,"top":1,"rgt":1,"btm":0,"lft":1,"hint":"12X"}],[{"cageId":30,"position":57,"value":7,"top":0,"rgt":1,"btm":1,"lft":1,"hint":""},{"cageId":34,"position":58,"value":5,"top":1,"rgt":1,"btm":1,"lft":1,"hint":"5"},{"cageId":25,"position":59,"value":3,"top":1,"rgt":1,"btm":1,"lft":1,"hint":"3"},{"cageId":37,"position":60,"value":8,"top":1,"rgt":1,"btm":1,"lft":1,"hint":"8"},{"cageId":31,"position":61,"value":1,"top":0,"rgt":1,"btm":1,"lft":1,"hint":""},{"cageId":35,"position":62,"value":6,"top":1,"rgt":1,"btm":1,"lft":1,"hint":"6"},{"cageId":29,"position":63,"value":2,"top":1,"rgt":1,"btm":1,"lft":1,"hint":"2"},{"cageId":33,"position":64,"value":4,"top":0,"rgt":1,"btm":1,"lft":1,"hint":""}]]}
